mcping/__init__.py
mcping/__main__.py
mcping/cli.py
mcping/exceptions.py
mcping-0.3.0.dist-info/METADATA
mcping-0.3.0.dist-info/WHEEL
mcping-0.3.0.dist-info/entry_points.txt
mcping-0.3.0.dist-info/RECORD
