Metadata-Version: 2.1
Name: mcping
Version: 0.3.0
Summary: Get statuses from Minecraft servers
Home-page: https://gitlab.com/MysteryBlokHed/mcping
License: MIT or Apache-2.0
Author: Adam Thompson-Sharpe
Author-email: adamthompsonsharpe@gmail.com
Requires-Python: >=3.8,<4.0
Classifier: Intended Audience :: Developers
Classifier: Intended Audience :: End Users/Desktop
Classifier: License :: OSI Approved :: Apache Software License
Classifier: License :: OSI Approved :: MIT License
Classifier: License :: Other/Proprietary License
Classifier: Natural Language :: English
Classifier: Operating System :: OS Independent
Classifier: Programming Language :: Python
Classifier: Programming Language :: Python :: 3
Classifier: Programming Language :: Python :: 3.8
Classifier: Programming Language :: Python :: 3.9
Classifier: Programming Language :: Python :: 3.10
Classifier: Programming Language :: Python :: 3.11
Requires-Dist: mcstatus (>=11.0,<12.0)
Project-URL: Repository, https://gitlab.com/MysteryBlokHed/mcping
